simrat/__init__.py
simrat/__main__.py
102203201_simrat-1.0.0.dist-info/LICENSE
102203201_simrat-1.0.0.dist-info/METADATA
102203201_simrat-1.0.0.dist-info/WHEEL
102203201_simrat-1.0.0.dist-info/entry_points.txt
102203201_simrat-1.0.0.dist-info/top_level.txt
102203201_simrat-1.0.0.dist-info/RECORD
