Metadata-Version: 2.2
Name: 102203201-simrat
Version: 1.0.0
Summary: It gives the topsis analysis of your csv file with score and rankings.
Home-page: https://github.com/simratk05/topsis_py_package_simrat
Author: Simrat Kaur
Author-email: simrat.kms@gmail.com
License: MIT
Classifier: License :: OSI Approved :: MIT License
Classifier: Programming Language :: Python :: 3.6
Classifier: Programming Language :: Python :: 3.7
Classifier: Programming Language :: Python :: 3.8
Classifier: Programming Language :: Python :: 3.12
License-File: LICENSE
Requires-Dist: numpy
Requires-Dist: pandas
Dynamic: author
Dynamic: author-email
Dynamic: classifier
Dynamic: description
Dynamic: description-content-type
Dynamic: home-page
Dynamic: license
Dynamic: requires-dist
Dynamic: summary
